{
  "results": {
    "limit": 100,
    "numPages": 1160,
    "page": 1078,
    "total": 115910,
    "versions": [
      {
        "d": {
          "f": "20150630",
          "s": "20150118"
        },
        "f": {
          "id": "blacksburg-transit/359",
          "l": {
            "id": 264,
            "lat": 37.229573,
            "lng": -80.413939,
            "n": "Blacksburg",
            "pid": 138,
            "t": "Blacksburg, VA, USA"
          },
          "t": "Blacksburg Transit GTFS",
          "ty": "gtfs",
          "u": {
            "d": "https://www.bt4uclassic.org/gtfs/google_transit.zip"
          }
        },
        "id": "blacksburg-transit/359/20150402",
        "size": 3130655,
        "ts": 1427997926,
        "url": "https://transitfeeds.com/p/blacksburg-transit/359/20150402/download"
      },
      {
        "d": {
          "f": "20150430",
          "s": "20150401"
        },
        "f": {
          "id": "opentransit/353",
          "l": {
            "id": 259,
            "lat": 34.637987,
            "lng": 138.128127,
            "n": "Omaezaki",
            "pid": 257,
            "t": "Omaezaki, Shizuoka Prefecture, Japan"
          },
          "t": "Omaezaki Local Voluntary Operation Bus GTFS",
          "ty": "gtfs",
          "u": {
            "d": "http://opentrans.it/feed/gtfs/5634472569470976/google_transit.zip",
            "i": "http://opentrans.it/"
          }
        },
        "id": "opentransit/353/20150402",
        "size": 16995,
        "ts": 1427997916,
        "url": "https://transitfeeds.com/p/opentransit/353/20150402/download"
      },
      {
        "d": {
          "f": "20150430",
          "s": "20150401"
        },
        "f": {
          "id": "opentransit/354",
          "l": {
            "id": 260,
            "lat": 35.173882,
            "lng": 138.906729,
            "n": "Susono",
            "pid": 257,
            "t": "Susono, Shizuoka Prefecture, Japan"
          },
          "t": "Susonohru GTFS",
          "ty": "gtfs",
          "u": {
            "d": "http://opentrans.it/feed/gtfs/5649391675244544/google_transit.zip",
            "i": "http://opentrans.it/"
          }
        },
        "id": "opentransit/354/20150402",
        "size": 37625,
        "ts": 1427997916,
        "url": "https://transitfeeds.com/p/opentransit/354/20150402/download"
      },
      {
        "d": {
          "f": "20150430",
          "s": "20150401"
        },
        "f": {
          "id": "opentransit/352",
          "l": {
            "id": 258,
            "lat": 34.768767,
            "lng": 137.998168,
            "n": "Kakegawa",
            "pid": 257,
            "t": "Kakegawa, Shizuoka Prefecture, Japan"
          },
          "t": "Kakegawa Local Voluntary Operation Bus GTFS",
          "ty": "gtfs",
          "u": {
            "d": "http://opentrans.it/feed/gtfs/5707702298738688/google_transit.zip",
            "i": "http://opentrans.it/"
          }
        },
        "id": "opentransit/352/20150402",
        "size": 11098,
        "ts": 1427997915,
        "url": "https://transitfeeds.com/p/opentransit/352/20150402/download"
      },
      {
        "d": {
          "f": "20150928",
          "s": "20150402"
        },
        "f": {
          "id": "valley-metro/68",
          "l": {
            "id": 98,
            "lat": 33.448377,
            "lng": -112.074037,
            "n": "Phoenix",
            "pid": 97,
            "t": "Phoenix, AZ, USA"
          },
          "t": "Valley Metro GTFS",
          "ty": "gtfs",
          "u": {
            "d": "https://phoenixopendata.com/dataset/3eae9a4a-98b9-40c8-8df7-8c00c1756235/resource/28ccc0a5-49c8-495c-b91f-193de5ce2cb7/download/googletransit.zip",
            "i": "https://phoenixopendata.com/dataset/valley-metro-bus-schedule/resource/28ccc0a5-49c8-495c-b91f-193de5ce2cb7"
          }
        },
        "id": "valley-metro/68/20150402",
        "size": 9328163,
        "ts": 1427997665,
        "url": "https://transitfeeds.com/p/valley-metro/68/20150402/download"
      },
      {
        "d": {
          "f": "20150605",
          "s": "20150401"
        },
        "f": {
          "id": "metro-transit/179",
          "l": {
            "id": 150,
            "lat": 44.983334,
            "lng": -93.26667,
            "n": "Minneapolis",
            "pid": 148,
            "t": "Minneapolis, MN, USA"
          },
          "t": "Metro Transit GTFS",
          "ty": "gtfs",
          "u": {
            "d": "https://svc.metrotransit.org/mtgtfs/gtfs.zip",
            "i": "https://gisdata.mn.gov/dataset/us-mn-state-metc-trans-transit-schedule-google-fd"
          }
        },
        "id": "metro-transit/179/20150402",
        "size": 18080385,
        "ts": 1427997639,
        "url": "https://transitfeeds.com/p/metro-transit/179/20150402/download"
      },
      {
        "d": {
          "f": "20150626",
          "s": "20150103"
        },
        "f": {
          "id": "go-transit/32",
          "l": {
            "id": 49,
            "lat": 43.653226,
            "lng": -79.383184,
            "n": "Toronto",
            "pid": 46,
            "t": "Toronto, ON, Canada"
          },
          "t": "GO Transit GTFS",
          "ty": "gtfs",
          "u": {
            "d": "https://www.gotransit.com/static_files/gotransit/assets/Files/GO_GTFS.zip",
            "i": "https://www.gotransit.com/en/information-resources/software-developers"
          }
        },
        "id": "go-transit/32/20150402",
        "size": 5569848,
        "ts": 1427987735,
        "url": "https://transitfeeds.com/p/go-transit/32/20150402/download"
      },
      {
        "d": {
          "f": "20150509",
          "s": "20150401"
        },
        "f": {
          "id": "ttc/33",
          "l": {
            "id": 49,
            "lat": 43.653226,
            "lng": -79.383184,
            "n": "Toronto",
            "pid": 46,
            "t": "Toronto, ON, Canada"
          },
          "t": "TTC GTFS",
          "ty": "gtfs",
          "u": {
            "d": "http://opendata.toronto.ca/TTC/routes/OpenData_TTC_Schedules.zip",
            "i": "https://open.toronto.ca/dataset/ttc-routes-and-schedules/"
          }
        },
        "id": "ttc/33/20150402",
        "size": 30031122,
        "ts": 1427987723,
        "url": "https://transitfeeds.com/p/ttc/33/20150402/download"
      },
      {
        "d": {
          "f": "20150627",
          "s": "20150404"
        },
        "f": {
          "id": "mta/82",
          "l": {
            "id": 91,
            "lat": 40.714353,
            "lng": -74.005973,
            "n": "New York",
            "pid": 84,
            "t": "New York, NY, USA"
          },
          "t": "MTA Manhattan GTFS",
          "ty": "gtfs",
          "u": {
            "d": "http://web.mta.info/developers/data/nyct/bus/google_transit_manhattan.zip",
            "i": "http://mta.info/developers/download.html"
          }
        },
        "id": "mta/82/20150402",
        "size": 8150860,
        "ts": 1427987433,
        "url": "https://transitfeeds.com/p/mta/82/20150402/download"
      },
      {
        "d": {
          "f": "20150503",
          "s": "20150105"
        },
        "f": {
          "id": "rochester-genesee-regional-transportation-authority/231",
          "l": {
            "id": 184,
            "lat": 43.16103,
            "lng": -77.610922,
            "n": "Rochester",
            "pid": 84,
            "t": "Rochester, NY, USA"
          },
          "t": "RGRTA GTFS",
          "ty": "gtfs",
          "u": {
            "d": "http://scheduledata.rgrta.com/google_transit.zip"
          }
        },
        "id": "rochester-genesee-regional-transportation-authority/231/20150402",
        "size": 3799809,
        "ts": 1427987420,
        "url": "https://transitfeeds.com/p/rochester-genesee-regional-transportation-authority/231/20150402/download"
      },
      {
        "d": {
          "f": "20150627",
          "s": "20150405"
        },
        "f": {
          "id": "mta/81",
          "l": {
            "id": 116,
            "lat": 40.85,
            "lng": -73.866667,
            "n": "Bronx",
            "pid": 91,
            "t": "Bronx, NY, USA"
          },
          "t": "MTA Bronx GTFS",
          "ty": "gtfs",
          "u": {
            "d": "http://web.mta.info/developers/data/nyct/bus/google_transit_bronx.zip",
            "i": "http://mta.info/developers/download.html"
          }
        },
        "id": "mta/81/20150402",
        "size": 9176871,
        "ts": 1427983826,
        "url": "https://transitfeeds.com/p/mta/81/20150402/download"
      },
      {
        "d": {
          "f": "20150928",
          "s": "20150402"
        },
        "f": {
          "id": "wmata/75",
          "l": {
            "id": 112,
            "lat": 38.907231,
            "lng": -77.036464,
            "n": "Washington",
            "pid": 111,
            "t": "Washington, DC, USA"
          },
          "t": "WMATA GTFS",
          "ty": "gtfs",
          "u": {
            "d": " https://api.wmata.com/gtfs/bus-gtfs-static.zip",
            "i": "https://developer.wmata.com/"
          }
        },
        "id": "wmata/75/20150402",
        "size": 14654979,
        "ts": 1427983533,
        "url": "https://transitfeeds.com/p/wmata/75/20150402/download"
      },
      {
        "d": {
          "f": "20150630",
          "s": "20141201"
        },
        "f": {
          "id": "transport-for-nsw/236",
          "l": {
            "id": 114,
            "lat": -33.867487,
            "lng": 151.20699,
            "n": "Sydney",
            "pid": 113,
            "t": "Sydney NSW, Australia"
          },
          "t": "Sydney Buses GTFS",
          "ty": "gtfs",
          "u": {
            "i": "https://opendata.transport.nsw.gov.au/dataset/public-transport-timetables-realtime"
          }
        },
        "id": "transport-for-nsw/236/20150402",
        "size": 33831025,
        "ts": 1427982020,
        "url": "https://transitfeeds.com/p/transport-for-nsw/236/20150402/download"
      },
      {
        "d": {
          "f": "20150705",
          "s": "20150402"
        },
        "f": {
          "id": "transporte-urbano-comarcal-de-pamplona/499",
          "l": {
            "id": 366,
            "lat": 42.812526,
            "lng": -1.645774,
            "n": "Pamplona",
            "pid": 166,
            "t": "Pamplona, Navarre, Spain"
          },
          "t": "TCC GTFS",
          "ty": "gtfs",
          "u": {
            "d": "http://86.109.125.18:88/gt/google_transit.zip"
          }
        },
        "id": "transporte-urbano-comarcal-de-pamplona/499/20150402",
        "size": 2399906,
        "ts": 1427972420,
        "url": "https://transitfeeds.com/p/transporte-urbano-comarcal-de-pamplona/499/20150402/download"
      },
      {
        "d": {
          "f": "20150701",
          "s": "20101108"
        },
        "f": {
          "id": "virginia-railway-express/250",
          "l": {
            "id": 138,
            "lat": 37.431573,
            "lng": -78.656894,
            "n": "Virginia",
            "pid": 31,
            "t": "Virginia, USA"
          },
          "t": "VRE GTFS",
          "ty": "gtfs",
          "u": {
            "d": "http://www.vre.org/gtfs/google_transit.zip",
            "i": "http://www.vre.org/programs/developer.html"
          }
        },
        "id": "virginia-railway-express/250/20150402",
        "size": 22829,
        "ts": 1427969118,
        "url": "https://transitfeeds.com/p/virginia-railway-express/250/20150402/download"
      },
      {
        "d": {
          "f": "20150531",
          "s": "20150401"
        },
        "f": {
          "id": "action-buses/3",
          "l": {
            "id": 8,
            "lat": -35.282,
            "lng": 149.128684,
            "n": "Canberra",
            "pid": 7,
            "t": "Canberra ACT, Australia"
          },
          "t": "Action Buses GTFS",
          "ty": "gtfs",
          "u": {
            "i": "http://www.transport.act.gov.au/getting-around/bus-services/mobile-apps"
          }
        },
        "id": "action-buses/3/20150402",
        "size": 6953197,
        "ts": 1427968823,
        "url": "https://transitfeeds.com/p/action-buses/3/20150402/download"
      },
      {
        "d": {
          "f": "20150613",
          "s": "20150201"
        },
        "f": {
          "id": "lane-transit-district/314",
          "l": {
            "id": 225,
            "lat": 44.052069,
            "lng": -123.086754,
            "n": "Eugene",
            "pid": 63,
            "t": "Eugene, OR, USA"
          },
          "t": "LTD GTFS",
          "ty": "gtfs",
          "u": {
            "d": "http://www.ltd.org/googletripplanning/20060917/google_transit.zip"
          }
        },
        "id": "lane-transit-district/314/20150402",
        "size": 1134514,
        "ts": 1427962202,
        "url": "https://transitfeeds.com/p/lane-transit-district/314/20150402/download"
      },
      {
        "d": {
          "f": "20150503",
          "s": "20150402"
        },
        "f": {
          "id": "ptv/497",
          "l": {
            "id": 323,
            "lat": -37.814107,
            "lng": 144.96328,
            "n": "Melbourne",
            "pid": 322,
            "t": "Melbourne VIC, Australia"
          },
          "t": "PTV GTFS",
          "ty": "gtfs",
          "u": {
            "d": "http://data.ptv.vic.gov.au/downloads/gtfs.zip",
            "i": "https://www.data.vic.gov.au/data/dataset/ptv-timetable-and-geographic-information-2015-gtfs"
          }
        },
        "id": "ptv/497/20150401",
        "size": 112935012,
        "ts": 1427955345,
        "url": "https://transitfeeds.com/p/ptv/497/20150401/download"
      },
      {
        "d": {
          "f": "20150430",
          "s": "20150331"
        },
        "f": {
          "id": "opentransit/353",
          "l": {
            "id": 259,
            "lat": 34.637987,
            "lng": 138.128127,
            "n": "Omaezaki",
            "pid": 257,
            "t": "Omaezaki, Shizuoka Prefecture, Japan"
          },
          "t": "Omaezaki Local Voluntary Operation Bus GTFS",
          "ty": "gtfs",
          "u": {
            "d": "http://opentrans.it/feed/gtfs/5634472569470976/google_transit.zip",
            "i": "http://opentrans.it/"
          }
        },
        "id": "opentransit/353/20150401-2",
        "size": 17021,
        "ts": 1427954423,
        "url": "https://transitfeeds.com/p/opentransit/353/20150401-2/download"
      },
      {
        "d": {
          "f": "20150430",
          "s": "20150331"
        },
        "f": {
          "id": "opentransit/354",
          "l": {
            "id": 260,
            "lat": 35.173882,
            "lng": 138.906729,
            "n": "Susono",
            "pid": 257,
            "t": "Susono, Shizuoka Prefecture, Japan"
          },
          "t": "Susonohru GTFS",
          "ty": "gtfs",
          "u": {
            "d": "http://opentrans.it/feed/gtfs/5649391675244544/google_transit.zip",
            "i": "http://opentrans.it/"
          }
        },
        "id": "opentransit/354/20150401-2",
        "size": 37701,
        "ts": 1427954423,
        "url": "https://transitfeeds.com/p/opentransit/354/20150401-2/download"
      },
      {
        "d": {
          "f": "20150430",
          "s": "20150331"
        },
        "f": {
          "id": "opentransit/352",
          "l": {
            "id": 258,
            "lat": 34.768767,
            "lng": 137.998168,
            "n": "Kakegawa",
            "pid": 257,
            "t": "Kakegawa, Shizuoka Prefecture, Japan"
          },
          "t": "Kakegawa Local Voluntary Operation Bus GTFS",
          "ty": "gtfs",
          "u": {
            "d": "http://opentrans.it/feed/gtfs/5707702298738688/google_transit.zip",
            "i": "http://opentrans.it/"
          }
        },
        "id": "opentransit/352/20150401-2",
        "size": 11279,
        "ts": 1427954422,
        "url": "https://transitfeeds.com/p/opentransit/352/20150401-2/download"
      },
      {
        "d": {
          "f": "20160101",
          "s": "20140101"
        },
        "f": {
          "id": "sandy-area-metro/480",
          "l": {
            "id": 348,
            "lat": 45.397343,
            "lng": -122.261476,
            "n": "Sandy",
            "pid": 63,
            "t": "Sandy, OR, USA"
          },
          "t": "SAM GTFS",
          "ty": "gtfs",
          "u": {
            "d": "http://oregon-gtfs.com/gtfs_data/sandy-or-us/sandy-or-us.zip"
          }
        },
        "id": "sandy-area-metro/480/20150401",
        "size": 39931,
        "ts": 1427952901,
        "url": "https://transitfeeds.com/p/sandy-area-metro/480/20150401/download"
      },
      {
        "d": {
          "f": "20150630",
          "s": "20150401"
        },
        "f": {
          "id": "transport-for-nsw/329",
          "l": {
            "id": 113,
            "lat": -31.253218,
            "lng": 146.921099,
            "n": "New South Wales",
            "pid": 2,
            "t": "New South Wales, Australia"
          },
          "t": "Sydney Light Rail Inner West GTFS",
          "ty": "gtfs",
          "u": {
            "i": "https://opendata.transport.nsw.gov.au/dataset/public-transport-timetables-realtime"
          }
        },
        "id": "transport-for-nsw/329/20150401",
        "size": 185839,
        "ts": 1427938716,
        "url": "https://transitfeeds.com/p/transport-for-nsw/329/20150401/download"
      },
      {
        "d": {
          "f": "20151231",
          "s": "20150101"
        },
        "f": {
          "id": "transport-for-nsw/326",
          "l": {
            "id": 113,
            "lat": -31.253218,
            "lng": 146.921099,
            "n": "New South Wales",
            "pid": 2,
            "t": "New South Wales, Australia"
          },
          "t": "Sydney Ferries GTFS",
          "ty": "gtfs",
          "u": {
            "i": "https://opendata.transport.nsw.gov.au/dataset/public-transport-timetables-realtime"
          }
        },
        "id": "transport-for-nsw/326/20150401",
        "size": 84189,
        "ts": 1427938707,
        "url": "https://transitfeeds.com/p/transport-for-nsw/326/20150401/download"
      },
      {
        "d": {
          "f": "20150502",
          "s": "20150104"
        },
        "f": {
          "id": "chattanooga-area-regional-transportation-authority/360",
          "l": {
            "id": 265,
            "lat": 35.04563,
            "lng": -85.30968,
            "n": "Chattanooga",
            "pid": 174,
            "t": "Chattanooga, TN, USA"
          },
          "t": "CARTA GTFS",
          "ty": "gtfs",
          "u": {
            "d": "https://www.gocarta.org/developers/GTFS.zip",
            "i": "http://www.gocarta.org/#developers"
          }
        },
        "id": "chattanooga-area-regional-transportation-authority/360/20150401",
        "size": 907025,
        "ts": 1427938205,
        "url": "https://transitfeeds.com/p/chattanooga-area-regional-transportation-authority/360/20150401/download"
      },
      {
        "d": {
          "f": "20150516",
          "s": "20141221"
        },
        "f": {
          "id": "champaign-urbana-mass-transit-district/162",
          "l": {
            "id": 147,
            "lat": 40.11642,
            "lng": -88.243383,
            "n": "Champaign",
            "pid": 145,
            "t": "Champaign, IL, USA"
          },
          "t": "Champaign-Urbana MTD GTFS",
          "ty": "gtfs",
          "u": {
            "d": "https://developer.cumtd.com/gtfs/google_transit.zip",
            "i": "http://developer.cumtd.com/"
          }
        },
        "id": "champaign-urbana-mass-transit-district/162/20150401",
        "size": 26483625,
        "ts": 1427925370,
        "url": "https://transitfeeds.com/p/champaign-urbana-mass-transit-district/162/20150401/download"
      },
      {
        "d": {
          "f": "20150627",
          "s": "20150331"
        },
        "f": {
          "id": "oc-transpo/30",
          "l": {
            "id": 47,
            "lat": 45.42153,
            "lng": -75.697193,
            "n": "Ottawa",
            "pid": 46,
            "t": "Ottawa, ON, Canada"
          },
          "t": "OC Transpo GTFS",
          "ty": "gtfs",
          "u": {
            "d": "http://www.octranspo1.com/files/google_transit.zip"
          }
        },
        "id": "oc-transpo/30/20150401",
        "size": 16887606,
        "ts": 1427923506,
        "url": "https://transitfeeds.com/p/oc-transpo/30/20150401/download"
      },
      {
        "d": {
          "f": "20150430",
          "s": "20150331"
        },
        "f": {
          "id": "opentransit/354",
          "l": {
            "id": 260,
            "lat": 35.173882,
            "lng": 138.906729,
            "n": "Susono",
            "pid": 257,
            "t": "Susono, Shizuoka Prefecture, Japan"
          },
          "t": "Susonohru GTFS",
          "ty": "gtfs",
          "u": {
            "d": "http://opentrans.it/feed/gtfs/5649391675244544/google_transit.zip",
            "i": "http://opentrans.it/"
          }
        },
        "id": "opentransit/354/20150401",
        "size": 37505,
        "ts": 1427911065,
        "url": "https://transitfeeds.com/p/opentransit/354/20150401/download"
      },
      {
        "d": {
          "f": "20150430",
          "s": "20150331"
        },
        "f": {
          "id": "opentransit/353",
          "l": {
            "id": 259,
            "lat": 34.637987,
            "lng": 138.128127,
            "n": "Omaezaki",
            "pid": 257,
            "t": "Omaezaki, Shizuoka Prefecture, Japan"
          },
          "t": "Omaezaki Local Voluntary Operation Bus GTFS",
          "ty": "gtfs",
          "u": {
            "d": "http://opentrans.it/feed/gtfs/5634472569470976/google_transit.zip",
            "i": "http://opentrans.it/"
          }
        },
        "id": "opentransit/353/20150401",
        "size": 17038,
        "ts": 1427911065,
        "url": "https://transitfeeds.com/p/opentransit/353/20150401/download"
      },
      {
        "d": {
          "f": "20150430",
          "s": "20150331"
        },
        "f": {
          "id": "opentransit/352",
          "l": {
            "id": 258,
            "lat": 34.768767,
            "lng": 137.998168,
            "n": "Kakegawa",
            "pid": 257,
            "t": "Kakegawa, Shizuoka Prefecture, Japan"
          },
          "t": "Kakegawa Local Voluntary Operation Bus GTFS",
          "ty": "gtfs",
          "u": {
            "d": "http://opentrans.it/feed/gtfs/5707702298738688/google_transit.zip",
            "i": "http://opentrans.it/"
          }
        },
        "id": "opentransit/352/20150401",
        "size": 11253,
        "ts": 1427911064,
        "url": "https://transitfeeds.com/p/opentransit/352/20150401/download"
      },
      {
        "d": {
          "f": "20150927",
          "s": "20150401"
        },
        "f": {
          "id": "valley-metro/68",
          "l": {
            "id": 98,
            "lat": 33.448377,
            "lng": -112.074037,
            "n": "Phoenix",
            "pid": 97,
            "t": "Phoenix, AZ, USA"
          },
          "t": "Valley Metro GTFS",
          "ty": "gtfs",
          "u": {
            "d": "https://phoenixopendata.com/dataset/3eae9a4a-98b9-40c8-8df7-8c00c1756235/resource/28ccc0a5-49c8-495c-b91f-193de5ce2cb7/download/googletransit.zip",
            "i": "https://phoenixopendata.com/dataset/valley-metro-bus-schedule/resource/28ccc0a5-49c8-495c-b91f-193de5ce2cb7"
          }
        },
        "id": "valley-metro/68/20150401",
        "size": 9328168,
        "ts": 1427910661,
        "url": "https://transitfeeds.com/p/valley-metro/68/20150401/download"
      },
      {
        "d": {
          "f": "20150502",
          "s": "20150402"
        },
        "f": {
          "id": "transport-for-nsw/305",
          "l": {
            "id": 113,
            "lat": -31.253218,
            "lng": 146.921099,
            "n": "New South Wales",
            "pid": 2,
            "t": "New South Wales, Australia"
          },
          "t": "Sydney Trains GTFS",
          "ty": "gtfs",
          "u": []
        },
        "id": "transport-for-nsw/305/20150401",
        "size": 5927545,
        "ts": 1427904612,
        "url": "https://transitfeeds.com/p/transport-for-nsw/305/20150401/download"
      },
      {
        "d": {
          "f": "20150630",
          "s": "20141201"
        },
        "f": {
          "id": "transport-for-nsw/236",
          "l": {
            "id": 114,
            "lat": -33.867487,
            "lng": 151.20699,
            "n": "Sydney",
            "pid": 113,
            "t": "Sydney NSW, Australia"
          },
          "t": "Sydney Buses GTFS",
          "ty": "gtfs",
          "u": {
            "i": "https://opendata.transport.nsw.gov.au/dataset/public-transport-timetables-realtime"
          }
        },
        "id": "transport-for-nsw/236/20150401",
        "size": 30053986,
        "ts": 1427903416,
        "url": "https://transitfeeds.com/p/transport-for-nsw/236/20150401/download"
      },
      {
        "d": {
          "f": "20150509",
          "s": "20150406"
        },
        "f": {
          "id": "ttc/33",
          "l": {
            "id": 49,
            "lat": 43.653226,
            "lng": -79.383184,
            "n": "Toronto",
            "pid": 46,
            "t": "Toronto, ON, Canada"
          },
          "t": "TTC GTFS",
          "ty": "gtfs",
          "u": {
            "d": "http://opendata.toronto.ca/TTC/routes/OpenData_TTC_Schedules.zip",
            "i": "https://open.toronto.ca/dataset/ttc-routes-and-schedules/"
          }
        },
        "id": "ttc/33/20150401",
        "size": 30030308,
        "ts": 1427900723,
        "url": "https://transitfeeds.com/p/ttc/33/20150401/download"
      },
      {
        "d": {
          "f": "20161231",
          "s": "20150309"
        },
        "f": {
          "id": "christchurch-metro/41",
          "l": {
            "id": 59,
            "lat": -43.532054,
            "lng": 172.636225,
            "n": "Christchurch",
            "pid": 28,
            "t": "Christchurch, New Zealand"
          },
          "t": "Metro GTFS",
          "ty": "gtfs",
          "u": {
            "d": "http://rtt.metroinfo.org.nz/rtt/public/utility/gtfs.aspx"
          }
        },
        "id": "christchurch-metro/41/20150401",
        "size": 2417279,
        "ts": 1427900709,
        "url": "https://transitfeeds.com/p/christchurch-metro/41/20150401/download"
      },
      {
        "d": {
          "f": "20150927",
          "s": "20150401"
        },
        "f": {
          "id": "wmata/75",
          "l": {
            "id": 112,
            "lat": 38.907231,
            "lng": -77.036464,
            "n": "Washington",
            "pid": 111,
            "t": "Washington, DC, USA"
          },
          "t": "WMATA GTFS",
          "ty": "gtfs",
          "u": {
            "d": " https://api.wmata.com/gtfs/bus-gtfs-static.zip",
            "i": "https://developer.wmata.com/"
          }
        },
        "id": "wmata/75/20150401",
        "size": 14654976,
        "ts": 1427896538,
        "url": "https://transitfeeds.com/p/wmata/75/20150401/download"
      },
      {
        "d": {
          "f": "20170101",
          "s": "20130101"
        },
        "f": {
          "id": "yosemite-area-regional-transportation-system/155",
          "l": {
            "id": 144,
            "lat": 37.74557,
            "lng": -119.593604,
            "n": "Yosemite Valley",
            "pid": 67,
            "t": "Yosemite Valley, CA, USA"
          },
          "t": "YARTS GTFS",
          "ty": "gtfs",
          "u": {
            "d": "http://data.trilliumtransit.com/gtfs/yosemite-ca-us/yosemite-ca-us.zip"
          }
        },
        "id": "yosemite-area-regional-transportation-system/155/20150401",
        "size": 358493,
        "ts": 1427887803,
        "url": "https://transitfeeds.com/p/yosemite-area-regional-transportation-system/155/20150401/download"
      },
      {
        "d": {
          "f": "20150705",
          "s": "20150401"
        },
        "f": {
          "id": "transporte-urbano-comarcal-de-pamplona/499",
          "l": {
            "id": 366,
            "lat": 42.812526,
            "lng": -1.645774,
            "n": "Pamplona",
            "pid": 166,
            "t": "Pamplona, Navarre, Spain"
          },
          "t": "TCC GTFS",
          "ty": "gtfs",
          "u": {
            "d": "http://86.109.125.18:88/gt/google_transit.zip"
          }
        },
        "id": "transporte-urbano-comarcal-de-pamplona/499/20150401",
        "size": 2399949,
        "ts": 1427885416,
        "url": "https://transitfeeds.com/p/transporte-urbano-comarcal-de-pamplona/499/20150401/download"
      },
      {
        "d": {
          "f": "20150620",
          "s": "20150331"
        },
        "f": {
          "id": "niagara-frontier-transportation-authority/230",
          "l": {
            "id": 183,
            "lat": 42.886447,
            "lng": -78.878369,
            "n": "Buffalo",
            "pid": 84,
            "t": "Buffalo, NY, USA"
          },
          "t": "NFTA GTFS",
          "ty": "gtfs",
          "u": {
            "d": "http://www.nfta.com/metro/__googletransit/google_transit.zip"
          }
        },
        "id": "niagara-frontier-transportation-authority/230/20150401",
        "size": 3444502,
        "ts": 1427882705,
        "url": "https://transitfeeds.com/p/niagara-frontier-transportation-authority/230/20150401/download"
      },
      {
        "d": {
          "f": "20150630",
          "s": "20101108"
        },
        "f": {
          "id": "virginia-railway-express/250",
          "l": {
            "id": 138,
            "lat": 37.431573,
            "lng": -78.656894,
            "n": "Virginia",
            "pid": 31,
            "t": "Virginia, USA"
          },
          "t": "VRE GTFS",
          "ty": "gtfs",
          "u": {
            "d": "http://www.vre.org/gtfs/google_transit.zip",
            "i": "http://www.vre.org/programs/developer.html"
          }
        },
        "id": "virginia-railway-express/250/20150401",
        "size": 22829,
        "ts": 1427882120,
        "url": "https://transitfeeds.com/p/virginia-railway-express/250/20150401/download"
      },
      {
        "d": {
          "f": "20150630",
          "s": "20150401"
        },
        "f": {
          "id": "transperth/2",
          "l": {
            "id": 6,
            "lat": -31.953004,
            "lng": 115.857469,
            "n": "Perth",
            "pid": 5,
            "t": "Perth WA, Australia"
          },
          "t": "Transperth GTFS",
          "ty": "gtfs",
          "u": {
            "d": "http://www.transperth.wa.gov.au/TimetablePDFs/GoogleTransit/Production/google_transit.zip",
            "i": "http://www.transperth.wa.gov.au/About/Spatial-Data-Access"
          }
        },
        "id": "transperth/2/20150401",
        "size": 16460589,
        "ts": 1427881861,
        "url": "https://transitfeeds.com/p/transperth/2/20150401/download"
      },
      {
        "d": {
          "f": "20150613",
          "s": "20150201"
        },
        "f": {
          "id": "lane-transit-district/314",
          "l": {
            "id": 225,
            "lat": 44.052069,
            "lng": -123.086754,
            "n": "Eugene",
            "pid": 63,
            "t": "Eugene, OR, USA"
          },
          "t": "LTD GTFS",
          "ty": "gtfs",
          "u": {
            "d": "http://www.ltd.org/googletripplanning/20060917/google_transit.zip"
          }
        },
        "id": "lane-transit-district/314/20150401",
        "size": 1136906,
        "ts": 1427875202,
        "url": "https://transitfeeds.com/p/lane-transit-district/314/20150401/download"
      },
      {
        "d": {
          "f": "20150430",
          "s": "20150330"
        },
        "f": {
          "id": "opentransit/354",
          "l": {
            "id": 260,
            "lat": 35.173882,
            "lng": 138.906729,
            "n": "Susono",
            "pid": 257,
            "t": "Susono, Shizuoka Prefecture, Japan"
          },
          "t": "Susonohru GTFS",
          "ty": "gtfs",
          "u": {
            "d": "http://opentrans.it/feed/gtfs/5649391675244544/google_transit.zip",
            "i": "http://opentrans.it/"
          }
        },
        "id": "opentransit/354/20150331-2",
        "size": 37787,
        "ts": 1427867224,
        "url": "https://transitfeeds.com/p/opentransit/354/20150331-2/download"
      },
      {
        "d": {
          "f": "20150430",
          "s": "20150330"
        },
        "f": {
          "id": "opentransit/353",
          "l": {
            "id": 259,
            "lat": 34.637987,
            "lng": 138.128127,
            "n": "Omaezaki",
            "pid": 257,
            "t": "Omaezaki, Shizuoka Prefecture, Japan"
          },
          "t": "Omaezaki Local Voluntary Operation Bus GTFS",
          "ty": "gtfs",
          "u": {
            "d": "http://opentrans.it/feed/gtfs/5634472569470976/google_transit.zip",
            "i": "http://opentrans.it/"
          }
        },
        "id": "opentransit/353/20150331-2",
        "size": 17216,
        "ts": 1427867223,
        "url": "https://transitfeeds.com/p/opentransit/353/20150331-2/download"
      },
      {
        "d": {
          "f": "20150430",
          "s": "20150330"
        },
        "f": {
          "id": "opentransit/352",
          "l": {
            "id": 258,
            "lat": 34.768767,
            "lng": 137.998168,
            "n": "Kakegawa",
            "pid": 257,
            "t": "Kakegawa, Shizuoka Prefecture, Japan"
          },
          "t": "Kakegawa Local Voluntary Operation Bus GTFS",
          "ty": "gtfs",
          "u": {
            "d": "http://opentrans.it/feed/gtfs/5707702298738688/google_transit.zip",
            "i": "http://opentrans.it/"
          }
        },
        "id": "opentransit/352/20150331-2",
        "size": 11196,
        "ts": 1427867223,
        "url": "https://transitfeeds.com/p/opentransit/352/20150331-2/download"
      },
      {
        "d": {
          "f": "20151231",
          "s": "20150331"
        },
        "f": {
          "id": "emt-madrid/212",
          "l": {
            "id": 167,
            "lat": 40.416775,
            "lng": -3.70379,
            "n": "Madrid",
            "pid": 166,
            "t": "Madrid, Spain"
          },
          "t": "EMT GTFS",
          "ty": "gtfs",
          "u": {
            "d": "https://servicios.emtmadrid.es:8443/gtfs/transitemt.zip"
          }
        },
        "id": "emt-madrid/212/20150331",
        "size": 13558190,
        "ts": 1427867211,
        "url": "https://transitfeeds.com/p/emt-madrid/212/20150331/download"
      },
      {
        "d": {
          "f": "20251231",
          "s": "20140403"
        },
        "f": {
          "id": "ptv/422",
          "l": {
            "id": 323,
            "lat": -37.814107,
            "lng": 144.96328,
            "n": "Melbourne",
            "pid": 322,
            "t": "Melbourne VIC, Australia"
          },
          "t": "PTV GTFS - TransitTimes",
          "ty": "gtfs",
          "u": []
        },
        "id": "ptv/422/20150331-3",
        "size": 25253609,
        "ts": 1427862209,
        "url": "https://transitfeeds.com/p/ptv/422/20150331-3/download"
      },
      {
        "d": {
          "f": "20151231",
          "s": "20150101"
        },
        "f": {
          "id": "transport-for-nsw/326",
          "l": {
            "id": 113,
            "lat": -31.253218,
            "lng": 146.921099,
            "n": "New South Wales",
            "pid": 2,
            "t": "New South Wales, Australia"
          },
          "t": "Sydney Ferries GTFS",
          "ty": "gtfs",
          "u": {
            "i": "https://opendata.transport.nsw.gov.au/dataset/public-transport-timetables-realtime"
          }
        },
        "id": "transport-for-nsw/326/20150331",
        "size": 83982,
        "ts": 1427859903,
        "url": "https://transitfeeds.com/p/transport-for-nsw/326/20150331/download"
      },
      {
        "d": {
          "f": "20150501",
          "s": "20150329"
        },
        "f": {
          "id": "bkk/42",
          "l": {
            "id": 62,
            "lat": 47.497912,
            "lng": 19.040235,
            "n": "Budapest",
            "pid": 617,
            "t": "Budapest, Hungary"
          },
          "t": "BKK GTFS",
          "ty": "gtfs",
          "u": {
            "d": "https://www.bkk.hu/gtfs/budapest_gtfs.zip"
          }
        },
        "id": "bkk/42/20150331",
        "size": 37089029,
        "ts": 1427852715,
        "url": "https://transitfeeds.com/p/bkk/42/20150331/download"
      },
      {
        "d": {
          "f": "20150502",
          "s": "20150104"
        },
        "f": {
          "id": "chattanooga-area-regional-transportation-authority/360",
          "l": {
            "id": 265,
            "lat": 35.04563,
            "lng": -85.30968,
            "n": "Chattanooga",
            "pid": 174,
            "t": "Chattanooga, TN, USA"
          },
          "t": "CARTA GTFS",
          "ty": "gtfs",
          "u": {
            "d": "https://www.gocarta.org/developers/GTFS.zip",
            "i": "http://www.gocarta.org/#developers"
          }
        },
        "id": "chattanooga-area-regional-transportation-authority/360/20150331",
        "size": 907025,
        "ts": 1427851266,
        "url": "https://transitfeeds.com/p/chattanooga-area-regional-transportation-authority/360/20150331/download"
      },
      {
        "d": {
          "f": "20251231",
          "s": "20140403"
        },
        "f": {
          "id": "ptv/422",
          "l": {
            "id": 323,
            "lat": -37.814107,
            "lng": 144.96328,
            "n": "Melbourne",
            "pid": 322,
            "t": "Melbourne VIC, Australia"
          },
          "t": "PTV GTFS - TransitTimes",
          "ty": "gtfs",
          "u": []
        },
        "id": "ptv/422/20150331-2",
        "size": 271561,
        "ts": 1427843104,
        "url": "https://transitfeeds.com/p/ptv/422/20150331-2/download"
      },
      {
        "d": {
          "f": "20150430",
          "s": "20150331"
        },
        "f": {
          "id": "transporte-urbano-comarcal-de-pamplona/499",
          "l": {
            "id": 366,
            "lat": 42.812526,
            "lng": -1.645774,
            "n": "Pamplona",
            "pid": 166,
            "t": "Pamplona, Navarre, Spain"
          },
          "t": "TCC GTFS",
          "ty": "gtfs",
          "u": {
            "d": "http://86.109.125.18:88/gt/google_transit.zip"
          }
        },
        "id": "transporte-urbano-comarcal-de-pamplona/499/20150331",
        "size": 2394847,
        "ts": 1427842036,
        "url": "https://transitfeeds.com/p/transporte-urbano-comarcal-de-pamplona/499/20150331/download"
      },
      {
        "d": {
          "f": "20160501",
          "s": "20140926"
        },
        "f": {
          "id": "metrolink/332",
          "l": {
            "id": 154,
            "lat": 34.052234,
            "lng": -118.243685,
            "n": "Los Angeles",
            "pid": 67,
            "t": "Los Angeles, CA, USA"
          },
          "t": "Metrolink GTFS",
          "ty": "gtfs",
          "u": {
            "d": "https://www.metrolinktrains.com/globalassets/about/gtfs/gtfs.zip",
            "i": "https://www.metrolinktrains.com/about/gtfs/"
          }
        },
        "id": "metrolink/332/20150331",
        "size": 90142,
        "ts": 1427839204,
        "url": "https://transitfeeds.com/p/metrolink/332/20150331/download"
      },
      {
        "d": {
          "f": "20150912",
          "s": "20150329"
        },
        "f": {
          "id": "trimet/43",
          "l": {
            "id": 64,
            "lat": 45.523452,
            "lng": -122.676207,
            "n": "Portland",
            "pid": 63,
            "t": "Portland, OR, USA"
          },
          "t": "TriMet GTFS",
          "ty": "gtfs",
          "u": {
            "d": "http://developer.trimet.org/schedule/gtfs.zip",
            "i": "http://developer.trimet.org/GTFS.shtml"
          }
        },
        "id": "trimet/43/20150331",
        "size": 22013693,
        "ts": 1427838610,
        "url": "https://transitfeeds.com/p/trimet/43/20150331/download"
      },
      {
        "d": {
          "f": "20150613",
          "s": "20150329"
        },
        "f": {
          "id": "samtrans/144",
          "l": {
            "id": 68,
            "lat": 37.774929,
            "lng": -122.419415,
            "n": "San Francisco",
            "pid": 67,
            "t": "San Francisco, CA, USA"
          },
          "t": "SamTrans GTFS",
          "ty": "gtfs",
          "u": {
            "i": "http://www.samtrans.com/Developer.html"
          }
        },
        "id": "samtrans/144/20150331",
        "size": 2501829,
        "ts": 1427838339,
        "url": "https://transitfeeds.com/p/samtrans/144/20150331/download"
      },
      {
        "d": {
          "f": "20150425",
          "s": "20141224"
        },
        "f": {
          "id": "st-albert-transit/498",
          "l": {
            "id": 365,
            "lat": 53.630475,
            "lng": -113.625642,
            "n": "Saint Albert",
            "pid": 42,
            "t": "Saint Albert, AB, Canada"
          },
          "t": "St Albert Transit GTFS",
          "ty": "gtfs",
          "u": {
            "d": "https://stalbert.ca/site/assets/files/3840/google_transit.zip",
            "i": "https://stalbert.ca/city/transit/tools/open-data-gtfs/"
          }
        },
        "id": "st-albert-transit/498/20150331",
        "size": 408432,
        "ts": 1427838246,
        "url": "https://transitfeeds.com/p/st-albert-transit/498/20150331/download"
      },
      {
        "d": {
          "f": "20150907",
          "s": "20150331"
        },
        "f": {
          "id": "massdot/104",
          "l": {
            "id": 92,
            "lat": 42.407211,
            "lng": -71.382437,
            "n": "Massachusetts",
            "pid": 31,
            "t": "Massachusetts, USA"
          },
          "t": "PVTA GTFS",
          "ty": "gtfs",
          "u": {
            "d": "http://www.pvta.com/g_trans/google_transit.zip",
            "i": "http://www.massdot.state.ma.us/DevelopersData.aspx"
          }
        },
        "id": "massdot/104/20150331",
        "size": 2324239,
        "ts": 1427836534,
        "url": "https://transitfeeds.com/p/massdot/104/20150331/download"
      },
      {
        "d": {
          "f": "20150606",
          "s": "20150201"
        },
        "f": {
          "id": "fort-worth-transportation-authority/56",
          "l": {
            "id": 86,
            "lat": 32.725409,
            "lng": -97.32085,
            "n": "Fort Worth",
            "pid": 35,
            "t": "Fort Worth, TX, USA"
          },
          "t": "FWTA GTFS",
          "ty": "gtfs",
          "u": {
            "d": "ftp://ftp.fwta.org/fwtatransitdata.zip",
            "i": "http://www.fwta.org/TransitDataGTFS.aspx"
          }
        },
        "id": "fort-worth-transportation-authority/56/20150331",
        "size": 1398120,
        "ts": 1427836520,
        "url": "https://transitfeeds.com/p/fort-worth-transportation-authority/56/20150331/download"
      },
      {
        "d": {
          "f": "20150430",
          "s": "20150330"
        },
        "f": {
          "id": "opentransit/354",
          "l": {
            "id": 260,
            "lat": 35.173882,
            "lng": 138.906729,
            "n": "Susono",
            "pid": 257,
            "t": "Susono, Shizuoka Prefecture, Japan"
          },
          "t": "Susonohru GTFS",
          "ty": "gtfs",
          "u": {
            "d": "http://opentrans.it/feed/gtfs/5649391675244544/google_transit.zip",
            "i": "http://opentrans.it/"
          }
        },
        "id": "opentransit/354/20150331",
        "size": 36858,
        "ts": 1427823699,
        "url": "https://transitfeeds.com/p/opentransit/354/20150331/download"
      },
      {
        "d": {
          "f": "20150430",
          "s": "20150330"
        },
        "f": {
          "id": "opentransit/353",
          "l": {
            "id": 259,
            "lat": 34.637987,
            "lng": 138.128127,
            "n": "Omaezaki",
            "pid": 257,
            "t": "Omaezaki, Shizuoka Prefecture, Japan"
          },
          "t": "Omaezaki Local Voluntary Operation Bus GTFS",
          "ty": "gtfs",
          "u": {
            "d": "http://opentrans.it/feed/gtfs/5634472569470976/google_transit.zip",
            "i": "http://opentrans.it/"
          }
        },
        "id": "opentransit/353/20150331",
        "size": 17019,
        "ts": 1427823698,
        "url": "https://transitfeeds.com/p/opentransit/353/20150331/download"
      },
      {
        "d": {
          "f": "20150430",
          "s": "20150330"
        },
        "f": {
          "id": "opentransit/352",
          "l": {
            "id": 258,
            "lat": 34.768767,
            "lng": 137.998168,
            "n": "Kakegawa",
            "pid": 257,
            "t": "Kakegawa, Shizuoka Prefecture, Japan"
          },
          "t": "Kakegawa Local Voluntary Operation Bus GTFS",
          "ty": "gtfs",
          "u": {
            "d": "http://opentrans.it/feed/gtfs/5707702298738688/google_transit.zip",
            "i": "http://opentrans.it/"
          }
        },
        "id": "opentransit/352/20150331",
        "size": 11203,
        "ts": 1427823698,
        "url": "https://transitfeeds.com/p/opentransit/352/20150331/download"
      },
      {
        "d": {
          "f": "20150926",
          "s": "20150331"
        },
        "f": {
          "id": "valley-metro/68",
          "l": {
            "id": 98,
            "lat": 33.448377,
            "lng": -112.074037,
            "n": "Phoenix",
            "pid": 97,
            "t": "Phoenix, AZ, USA"
          },
          "t": "Valley Metro GTFS",
          "ty": "gtfs",
          "u": {
            "d": "https://phoenixopendata.com/dataset/3eae9a4a-98b9-40c8-8df7-8c00c1756235/resource/28ccc0a5-49c8-495c-b91f-193de5ce2cb7/download/googletransit.zip",
            "i": "https://phoenixopendata.com/dataset/valley-metro-bus-schedule/resource/28ccc0a5-49c8-495c-b91f-193de5ce2cb7"
          }
        },
        "id": "valley-metro/68/20150331",
        "size": 9328174,
        "ts": 1427823683,
        "url": "https://transitfeeds.com/p/valley-metro/68/20150331/download"
      },
      {
        "d": {
          "f": "20150501",
          "s": "20150401"
        },
        "f": {
          "id": "transport-for-nsw/305",
          "l": {
            "id": 113,
            "lat": -31.253218,
            "lng": 146.921099,
            "n": "New South Wales",
            "pid": 2,
            "t": "New South Wales, Australia"
          },
          "t": "Sydney Trains GTFS",
          "ty": "gtfs",
          "u": []
        },
        "id": "transport-for-nsw/305/20150331",
        "size": 5928125,
        "ts": 1427817612,
        "url": "https://transitfeeds.com/p/transport-for-nsw/305/20150331/download"
      },
      {
        "d": {
          "f": "20150630",
          "s": "20141201"
        },
        "f": {
          "id": "transport-for-nsw/236",
          "l": {
            "id": 114,
            "lat": -33.867487,
            "lng": 151.20699,
            "n": "Sydney",
            "pid": 113,
            "t": "Sydney NSW, Australia"
          },
          "t": "Sydney Buses GTFS",
          "ty": "gtfs",
          "u": {
            "i": "https://opendata.transport.nsw.gov.au/dataset/public-transport-timetables-realtime"
          }
        },
        "id": "transport-for-nsw/236/20150331",
        "size": 29754107,
        "ts": 1427816416,
        "url": "https://transitfeeds.com/p/transport-for-nsw/236/20150331/download"
      },
      {
        "d": {
          "f": "20150614",
          "s": "20150323"
        },
        "f": {
          "id": "trafiklab/50",
          "l": {
            "id": 77,
            "lat": 60.128161,
            "lng": 18.643501,
            "n": "Sweden",
            "pid": 60,
            "t": "Sweden"
          },
          "t": "TrafikLab GTFS",
          "ty": "gtfs",
          "u": {
            "i": "http://www.trafiklab.se/api"
          }
        },
        "id": "trafiklab/50/20150331",
        "size": 37206288,
        "ts": 1427813720,
        "url": "https://transitfeeds.com/p/trafiklab/50/20150331/download"
      },
      {
        "d": {
          "f": "20150606",
          "s": "20141207"
        },
        "f": {
          "id": "thebus-honolulu/57",
          "l": {
            "id": 88,
            "lat": 21.306944,
            "lng": -157.858333,
            "n": "Honolulu",
            "pid": 87,
            "t": "Honolulu, HI, USA"
          },
          "t": "TheBus GTFS",
          "ty": "gtfs",
          "u": {
            "d": "http://webapps.thebus.org/transitdata/Production/google_transit.zip"
          }
        },
        "id": "thebus-honolulu/57/20150331",
        "size": 14917103,
        "ts": 1427809815,
        "url": "https://transitfeeds.com/p/thebus-honolulu/57/20150331/download"
      },
      {
        "d": {
          "f": "20150926",
          "s": "20150331"
        },
        "f": {
          "id": "wmata/75",
          "l": {
            "id": 112,
            "lat": 38.907231,
            "lng": -77.036464,
            "n": "Washington",
            "pid": 111,
            "t": "Washington, DC, USA"
          },
          "t": "WMATA GTFS",
          "ty": "gtfs",
          "u": {
            "d": " https://api.wmata.com/gtfs/bus-gtfs-static.zip",
            "i": "https://developer.wmata.com/"
          }
        },
        "id": "wmata/75/20150331",
        "size": 14654631,
        "ts": 1427809538,
        "url": "https://transitfeeds.com/p/wmata/75/20150331/download"
      },
      {
        "d": {
          "f": "20170101",
          "s": "20150101"
        },
        "f": {
          "id": "anaheim-resort-transportation/410",
          "l": {
            "id": 312,
            "lat": 33.835293,
            "lng": -117.914504,
            "n": "Anaheim",
            "pid": 67,
            "t": "Anaheim, CA, USA"
          },
          "t": "ART GTFS",
          "ty": "gtfs",
          "u": {
            "d": "http://data.trilliumtransit.com/gtfs/anaheim-ca-us/anaheim-ca-us.zip",
            "i": "http://rideart.org/gtfs/"
          }
        },
        "id": "anaheim-resort-transportation/410/20150331",
        "size": 547160,
        "ts": 1427802605,
        "url": "https://transitfeeds.com/p/anaheim-resort-transportation/410/20150331/download"
      },
      {
        "d": {
          "f": "20251231",
          "s": "20150223"
        },
        "f": {
          "id": "ptv/422",
          "l": {
            "id": 323,
            "lat": -37.814107,
            "lng": 144.96328,
            "n": "Melbourne",
            "pid": 322,
            "t": "Melbourne VIC, Australia"
          },
          "t": "PTV GTFS - TransitTimes",
          "ty": "gtfs",
          "u": []
        },
        "id": "ptv/422/20150331",
        "size": 20076701,
        "ts": 1427799615,
        "url": "https://transitfeeds.com/p/ptv/422/20150331/download"
      },
      {
        "d": {
          "f": "20150629",
          "s": "20101108"
        },
        "f": {
          "id": "virginia-railway-express/250",
          "l": {
            "id": 138,
            "lat": 37.431573,
            "lng": -78.656894,
            "n": "Virginia",
            "pid": 31,
            "t": "Virginia, USA"
          },
          "t": "VRE GTFS",
          "ty": "gtfs",
          "u": {
            "d": "http://www.vre.org/gtfs/google_transit.zip",
            "i": "http://www.vre.org/programs/developer.html"
          }
        },
        "id": "virginia-railway-express/250/20150331",
        "size": 22829,
        "ts": 1427795117,
        "url": "https://transitfeeds.com/p/virginia-railway-express/250/20150331/download"
      },
      {
        "d": {
          "f": "20150426",
          "s": "20150413"
        },
        "f": {
          "id": "star/208",
          "l": {
            "id": 162,
            "lat": 48.856614,
            "lng": 2.352222,
            "n": "Paris",
            "pid": 161,
            "t": "Paris, France"
          },
          "t": "STAR GTFS",
          "ty": "gtfs",
          "u": {
            "i": "https://data.explore.star.fr/explore/dataset/tco-busmetro-horaires-gtfs-versions-td/information/"
          }
        },
        "id": "star/208/20150331",
        "size": 4479505,
        "ts": 1427794826,
        "url": "https://transitfeeds.com/p/star/208/20150331/download"
      },
      {
        "d": {
          "f": "20150613",
          "s": "20150201"
        },
        "f": {
          "id": "lane-transit-district/314",
          "l": {
            "id": 225,
            "lat": 44.052069,
            "lng": -123.086754,
            "n": "Eugene",
            "pid": 63,
            "t": "Eugene, OR, USA"
          },
          "t": "LTD GTFS",
          "ty": "gtfs",
          "u": {
            "d": "http://www.ltd.org/googletripplanning/20060917/google_transit.zip"
          }
        },
        "id": "lane-transit-district/314/20150331",
        "size": 1141727,
        "ts": 1427788202,
        "url": "https://transitfeeds.com/p/lane-transit-district/314/20150331/download"
      },
      {
        "d": {
          "f": "20150430",
          "s": "20150325"
        },
        "f": {
          "id": "ptv/497",
          "l": {
            "id": 323,
            "lat": -37.814107,
            "lng": 144.96328,
            "n": "Melbourne",
            "pid": 322,
            "t": "Melbourne VIC, Australia"
          },
          "t": "PTV GTFS",
          "ty": "gtfs",
          "u": {
            "d": "http://data.ptv.vic.gov.au/downloads/gtfs.zip",
            "i": "https://www.data.vic.gov.au/data/dataset/ptv-timetable-and-geographic-information-2015-gtfs"
          }
        },
        "id": "ptv/497/20150330",
        "size": 127517449,
        "ts": 1427780394,
        "url": "https://transitfeeds.com/p/ptv/497/20150330/download"
      },
      {
        "d": {
          "f": "20150430",
          "s": "20150329"
        },
        "f": {
          "id": "opentransit/354",
          "l": {
            "id": 260,
            "lat": 35.173882,
            "lng": 138.906729,
            "n": "Susono",
            "pid": 257,
            "t": "Susono, Shizuoka Prefecture, Japan"
          },
          "t": "Susonohru GTFS",
          "ty": "gtfs",
          "u": {
            "d": "http://opentrans.it/feed/gtfs/5649391675244544/google_transit.zip",
            "i": "http://opentrans.it/"
          }
        },
        "id": "opentransit/354/20150330-2",
        "size": 37644,
        "ts": 1427780181,
        "url": "https://transitfeeds.com/p/opentransit/354/20150330-2/download"
      },
      {
        "d": {
          "f": "20150430",
          "s": "20150329"
        },
        "f": {
          "id": "opentransit/352",
          "l": {
            "id": 258,
            "lat": 34.768767,
            "lng": 137.998168,
            "n": "Kakegawa",
            "pid": 257,
            "t": "Kakegawa, Shizuoka Prefecture, Japan"
          },
          "t": "Kakegawa Local Voluntary Operation Bus GTFS",
          "ty": "gtfs",
          "u": {
            "d": "http://opentrans.it/feed/gtfs/5707702298738688/google_transit.zip",
            "i": "http://opentrans.it/"
          }
        },
        "id": "opentransit/352/20150330-2",
        "size": 11204,
        "ts": 1427780180,
        "url": "https://transitfeeds.com/p/opentransit/352/20150330-2/download"
      },
      {
        "d": {
          "f": "20150430",
          "s": "20150329"
        },
        "f": {
          "id": "opentransit/353",
          "l": {
            "id": 259,
            "lat": 34.637987,
            "lng": 138.128127,
            "n": "Omaezaki",
            "pid": 257,
            "t": "Omaezaki, Shizuoka Prefecture, Japan"
          },
          "t": "Omaezaki Local Voluntary Operation Bus GTFS",
          "ty": "gtfs",
          "u": {
            "d": "http://opentrans.it/feed/gtfs/5634472569470976/google_transit.zip",
            "i": "http://opentrans.it/"
          }
        },
        "id": "opentransit/353/20150330-2",
        "size": 17092,
        "ts": 1427780180,
        "url": "https://transitfeeds.com/p/opentransit/353/20150330-2/download"
      },
      {
        "d": {
          "f": "20150705",
          "s": "20150331"
        },
        "f": {
          "id": "adelaide-metro/1",
          "l": {
            "id": 4,
            "lat": -34.928621,
            "lng": 138.599959,
            "n": "Adelaide",
            "pid": 3,
            "t": "Adelaide SA, Australia"
          },
          "t": "Adelaide Metro GTFS",
          "ty": "gtfs",
          "u": {
            "d": "http://adelaidemetro.com.au/GTFS/google_transit.zip",
            "i": "http://www.adelaidemetro.com.au/Developer-Information"
          }
        },
        "id": "adelaide-metro/1/20150330",
        "size": 11612425,
        "ts": 1427780162,
        "url": "https://transitfeeds.com/p/adelaide-metro/1/20150330/download"
      },
      {
        "d": {
          "f": "20150628",
          "s": "20150330"
        },
        "f": {
          "id": "transport-for-nsw/237",
          "l": {
            "id": 113,
            "lat": -31.253218,
            "lng": 146.921099,
            "n": "New South Wales",
            "pid": 2,
            "t": "New South Wales, Australia"
          },
          "t": "Greater Sydney GTFS",
          "ty": "gtfs",
          "u": {
            "d": "https://opendata.transport.nsw.gov.au/api/download/9ca31d18-5efa-43ec-870d-258ee3388614",
            "i": "https://opendata.transport.nsw.gov.au/dataset/timetables-complete-gtfs"
          }
        },
        "id": "transport-for-nsw/237/20150330",
        "size": 113365340,
        "ts": 1427774207,
        "url": "https://transitfeeds.com/p/transport-for-nsw/237/20150330/download"
      },
      {
        "d": {
          "f": "20151004",
          "s": "20141214"
        },
        "f": {
          "id": "la-metro/184",
          "l": {
            "id": 154,
            "lat": 34.052234,
            "lng": -118.243685,
            "n": "Los Angeles",
            "pid": 67,
            "t": "Los Angeles, CA, USA"
          },
          "t": "LA Metro Bus GTFS",
          "ty": "gtfs",
          "u": {
            "d": "https://gitlab.com/LACMTA/gtfs_bus/raw/master/gtfs_bus.zip",
            "i": "http://developer.metro.net/introduction/gtfs-data/download-metros-gtfs-data/"
          }
        },
        "id": "la-metro/184/20150330",
        "size": 18505347,
        "ts": 1427765703,
        "url": "https://transitfeeds.com/p/la-metro/184/20150330/download"
      },
      {
        "d": {
          "f": "20150502",
          "s": "20150104"
        },
        "f": {
          "id": "chattanooga-area-regional-transportation-authority/360",
          "l": {
            "id": 265,
            "lat": 35.04563,
            "lng": -85.30968,
            "n": "Chattanooga",
            "pid": 174,
            "t": "Chattanooga, TN, USA"
          },
          "t": "CARTA GTFS",
          "ty": "gtfs",
          "u": {
            "d": "https://www.gocarta.org/developers/GTFS.zip",
            "i": "http://www.gocarta.org/#developers"
          }
        },
        "id": "chattanooga-area-regional-transportation-authority/360/20150330",
        "size": 907026,
        "ts": 1427764204,
        "url": "https://transitfeeds.com/p/chattanooga-area-regional-transportation-authority/360/20150330/download"
      },
      {
        "d": {
          "f": "20150627",
          "s": "20150404"
        },
        "f": {
          "id": "mta/85",
          "l": {
            "id": 91,
            "lat": 40.714353,
            "lng": -74.005973,
            "n": "New York",
            "pid": 84,
            "t": "New York, NY, USA"
          },
          "t": "NYC Bus Company GTFS",
          "ty": "gtfs",
          "u": {
            "d": "http://web.mta.info/developers/data/busco/google_transit.zip",
            "i": "http://mta.info/developers/download.html"
          }
        },
        "id": "mta/85/20150330",
        "size": 9578003,
        "ts": 1427751325,
        "url": "https://transitfeeds.com/p/mta/85/20150330/download"
      },
      {
        "d": {
          "f": "20150606",
          "s": "20150201"
        },
        "f": {
          "id": "fort-worth-transportation-authority/56",
          "l": {
            "id": 86,
            "lat": 32.725409,
            "lng": -97.32085,
            "n": "Fort Worth",
            "pid": 35,
            "t": "Fort Worth, TX, USA"
          },
          "t": "FWTA GTFS",
          "ty": "gtfs",
          "u": {
            "d": "ftp://ftp.fwta.org/fwtatransitdata.zip",
            "i": "http://www.fwta.org/TransitDataGTFS.aspx"
          }
        },
        "id": "fort-worth-transportation-authority/56/20150330",
        "size": 1397962,
        "ts": 1427749519,
        "url": "https://transitfeeds.com/p/fort-worth-transportation-authority/56/20150330/download"
      },
      {
        "d": {
          "f": "20150430",
          "s": "20150329"
        },
        "f": {
          "id": "opentransit/354",
          "l": {
            "id": 260,
            "lat": 35.173882,
            "lng": 138.906729,
            "n": "Susono",
            "pid": 257,
            "t": "Susono, Shizuoka Prefecture, Japan"
          },
          "t": "Susonohru GTFS",
          "ty": "gtfs",
          "u": {
            "d": "http://opentrans.it/feed/gtfs/5649391675244544/google_transit.zip",
            "i": "http://opentrans.it/"
          }
        },
        "id": "opentransit/354/20150330",
        "size": 37293,
        "ts": 1427736729,
        "url": "https://transitfeeds.com/p/opentransit/354/20150330/download"
      },
      {
        "d": {
          "f": "20150430",
          "s": "20150329"
        },
        "f": {
          "id": "opentransit/353",
          "l": {
            "id": 259,
            "lat": 34.637987,
            "lng": 138.128127,
            "n": "Omaezaki",
            "pid": 257,
            "t": "Omaezaki, Shizuoka Prefecture, Japan"
          },
          "t": "Omaezaki Local Voluntary Operation Bus GTFS",
          "ty": "gtfs",
          "u": {
            "d": "http://opentrans.it/feed/gtfs/5634472569470976/google_transit.zip",
            "i": "http://opentrans.it/"
          }
        },
        "id": "opentransit/353/20150330",
        "size": 17074,
        "ts": 1427736728,
        "url": "https://transitfeeds.com/p/opentransit/353/20150330/download"
      },
      {
        "d": {
          "f": "20150430",
          "s": "20150329"
        },
        "f": {
          "id": "opentransit/352",
          "l": {
            "id": 258,
            "lat": 34.768767,
            "lng": 137.998168,
            "n": "Kakegawa",
            "pid": 257,
            "t": "Kakegawa, Shizuoka Prefecture, Japan"
          },
          "t": "Kakegawa Local Voluntary Operation Bus GTFS",
          "ty": "gtfs",
          "u": {
            "d": "http://opentrans.it/feed/gtfs/5707702298738688/google_transit.zip",
            "i": "http://opentrans.it/"
          }
        },
        "id": "opentransit/352/20150330",
        "size": 11156,
        "ts": 1427736727,
        "url": "https://transitfeeds.com/p/opentransit/352/20150330/download"
      },
      {
        "d": {
          "f": "20150925",
          "s": "20150330"
        },
        "f": {
          "id": "valley-metro/68",
          "l": {
            "id": 98,
            "lat": 33.448377,
            "lng": -112.074037,
            "n": "Phoenix",
            "pid": 97,
            "t": "Phoenix, AZ, USA"
          },
          "t": "Valley Metro GTFS",
          "ty": "gtfs",
          "u": {
            "d": "https://phoenixopendata.com/dataset/3eae9a4a-98b9-40c8-8df7-8c00c1756235/resource/28ccc0a5-49c8-495c-b91f-193de5ce2cb7/download/googletransit.zip",
            "i": "https://phoenixopendata.com/dataset/valley-metro-bus-schedule/resource/28ccc0a5-49c8-495c-b91f-193de5ce2cb7"
          }
        },
        "id": "valley-metro/68/20150330",
        "size": 9328173,
        "ts": 1427736713,
        "url": "https://transitfeeds.com/p/valley-metro/68/20150330/download"
      },
      {
        "d": {
          "f": "20150605",
          "s": "20150325"
        },
        "f": {
          "id": "metro-transit/179",
          "l": {
            "id": 150,
            "lat": 44.983334,
            "lng": -93.26667,
            "n": "Minneapolis",
            "pid": 148,
            "t": "Minneapolis, MN, USA"
          },
          "t": "Metro Transit GTFS",
          "ty": "gtfs",
          "u": {
            "d": "https://svc.metrotransit.org/mtgtfs/gtfs.zip",
            "i": "https://gisdata.mn.gov/dataset/us-mn-state-metc-trans-transit-schedule-google-fd"
          }
        },
        "id": "metro-transit/179/20150330",
        "size": 18050414,
        "ts": 1427736685,
        "url": "https://transitfeeds.com/p/metro-transit/179/20150330/download"
      },
      {
        "d": {
          "f": "20151231",
          "s": "20150101"
        },
        "f": {
          "id": "fresno-area-express/315",
          "l": {
            "id": 226,
            "lat": 36.746842,
            "lng": -119.772587,
            "n": "Fresno",
            "pid": 67,
            "t": "Fresno, CA, USA"
          },
          "t": "FAX GTFS",
          "ty": "gtfs",
          "u": {
            "d": "https://gis4u.fresno.gov/downloads/zip/fax_gtfs.zip",
            "i": "https://www.fresno.gov/publicworks/developer-doorway/technical-library/"
          }
        },
        "id": "fresno-area-express/315/20150330",
        "size": 771582,
        "ts": 1427736620,
        "url": "https://transitfeeds.com/p/fresno-area-express/315/20150330/download"
      },
      {
        "d": {
          "f": "20150430",
          "s": "20150331"
        },
        "f": {
          "id": "transport-for-nsw/305",
          "l": {
            "id": 113,
            "lat": -31.253218,
            "lng": 146.921099,
            "n": "New South Wales",
            "pid": 2,
            "t": "New South Wales, Australia"
          },
          "t": "Sydney Trains GTFS",
          "ty": "gtfs",
          "u": []
        },
        "id": "transport-for-nsw/305/20150330",
        "size": 5389806,
        "ts": 1427730312,
        "url": "https://transitfeeds.com/p/transport-for-nsw/305/20150330/download"
      },
      {
        "d": {
          "f": "20150630",
          "s": "20141201"
        },
        "f": {
          "id": "transport-for-nsw/236",
          "l": {
            "id": 114,
            "lat": -33.867487,
            "lng": 151.20699,
            "n": "Sydney",
            "pid": 113,
            "t": "Sydney NSW, Australia"
          },
          "t": "Sydney Buses GTFS",
          "ty": "gtfs",
          "u": {
            "i": "https://opendata.transport.nsw.gov.au/dataset/public-transport-timetables-realtime"
          }
        },
        "id": "transport-for-nsw/236/20150330",
        "size": 27223034,
        "ts": 1427729416,
        "url": "https://transitfeeds.com/p/transport-for-nsw/236/20150330/download"
      },
      {
        "d": {
          "f": "20150614",
          "s": "20150323"
        },
        "f": {
          "id": "trafiklab/50",
          "l": {
            "id": 77,
            "lat": 60.128161,
            "lng": 18.643501,
            "n": "Sweden",
            "pid": 60,
            "t": "Sweden"
          },
          "t": "TrafikLab GTFS",
          "ty": "gtfs",
          "u": {
            "i": "http://www.trafiklab.se/api"
          }
        },
        "id": "trafiklab/50/20150330",
        "size": 44245761,
        "ts": 1427726419,
        "url": "https://transitfeeds.com/p/trafiklab/50/20150330/download"
      },
      {
        "d": {
          "f": "20150925",
          "s": "20150330"
        },
        "f": {
          "id": "wmata/75",
          "l": {
            "id": 112,
            "lat": 38.907231,
            "lng": -77.036464,
            "n": "Washington",
            "pid": 111,
            "t": "Washington, DC, USA"
          },
          "t": "WMATA GTFS",
          "ty": "gtfs",
          "u": {
            "d": " https://api.wmata.com/gtfs/bus-gtfs-static.zip",
            "i": "https://developer.wmata.com/"
          }
        },
        "id": "wmata/75/20150330",
        "size": 14654635,
        "ts": 1427722537,
        "url": "https://transitfeeds.com/p/wmata/75/20150330/download"
      },
      {
        "d": {
          "f": "20150628",
          "s": "20101108"
        },
        "f": {
          "id": "virginia-railway-express/250",
          "l": {
            "id": 138,
            "lat": 37.431573,
            "lng": -78.656894,
            "n": "Virginia",
            "pid": 31,
            "t": "Virginia, USA"
          },
          "t": "VRE GTFS",
          "ty": "gtfs",
          "u": {
            "d": "http://www.vre.org/gtfs/google_transit.zip",
            "i": "http://www.vre.org/programs/developer.html"
          }
        },
        "id": "virginia-railway-express/250/20150330",
        "size": 22829,
        "ts": 1427708111,
        "url": "https://transitfeeds.com/p/virginia-railway-express/250/20150330/download"
      },
      {
        "d": {
          "f": "20150516",
          "s": "20140820"
        },
        "f": {
          "id": "champaign-urbana-mass-transit-district/162",
          "l": {
            "id": 147,
            "lat": 40.11642,
            "lng": -88.243383,
            "n": "Champaign",
            "pid": 145,
            "t": "Champaign, IL, USA"
          },
          "t": "Champaign-Urbana MTD GTFS",
          "ty": "gtfs",
          "u": {
            "d": "https://developer.cumtd.com/gtfs/google_transit.zip",
            "i": "http://developer.cumtd.com/"
          }
        },
        "id": "champaign-urbana-mass-transit-district/162/20150330",
        "size": 26697269,
        "ts": 1427707862,
        "url": "https://transitfeeds.com/p/champaign-urbana-mass-transit-district/162/20150330/download"
      },
      {
        "d": {
          "f": "20150613",
          "s": "20150201"
        },
        "f": {
          "id": "lane-transit-district/314",
          "l": {
            "id": 225,
            "lat": 44.052069,
            "lng": -123.086754,
            "n": "Eugene",
            "pid": 63,
            "t": "Eugene, OR, USA"
          },
          "t": "LTD GTFS",
          "ty": "gtfs",
          "u": {
            "d": "http://www.ltd.org/googletripplanning/20060917/google_transit.zip"
          }
        },
        "id": "lane-transit-district/314/20150330",
        "size": 1142155,
        "ts": 1427701202,
        "url": "https://transitfeeds.com/p/lane-transit-district/314/20150330/download"
      },
      {
        "d": {
          "f": "20150430",
          "s": "20150328"
        },
        "f": {
          "id": "opentransit/353",
          "l": {
            "id": 259,
            "lat": 34.637987,
            "lng": 138.128127,
            "n": "Omaezaki",
            "pid": 257,
            "t": "Omaezaki, Shizuoka Prefecture, Japan"
          },
          "t": "Omaezaki Local Voluntary Operation Bus GTFS",
          "ty": "gtfs",
          "u": {
            "d": "http://opentrans.it/feed/gtfs/5634472569470976/google_transit.zip",
            "i": "http://opentrans.it/"
          }
        },
        "id": "opentransit/353/20150329-2",
        "size": 16995,
        "ts": 1427693180,
        "url": "https://transitfeeds.com/p/opentransit/353/20150329-2/download"
      },
      {
        "d": {
          "f": "20150430",
          "s": "20150328"
        },
        "f": {
          "id": "opentransit/354",
          "l": {
            "id": 260,
            "lat": 35.173882,
            "lng": 138.906729,
            "n": "Susono",
            "pid": 257,
            "t": "Susono, Shizuoka Prefecture, Japan"
          },
          "t": "Susonohru GTFS",
          "ty": "gtfs",
          "u": {
            "d": "http://opentrans.it/feed/gtfs/5649391675244544/google_transit.zip",
            "i": "http://opentrans.it/"
          }
        },
        "id": "opentransit/354/20150329-2",
        "size": 38639,
        "ts": 1427693180,
        "url": "https://transitfeeds.com/p/opentransit/354/20150329-2/download"
      },
      {
        "d": {
          "f": "20150430",
          "s": "20150328"
        },
        "f": {
          "id": "opentransit/352",
          "l": {
            "id": 258,
            "lat": 34.768767,
            "lng": 137.998168,
            "n": "Kakegawa",
            "pid": 257,
            "t": "Kakegawa, Shizuoka Prefecture, Japan"
          },
          "t": "Kakegawa Local Voluntary Operation Bus GTFS",
          "ty": "gtfs",
          "u": {
            "d": "http://opentrans.it/feed/gtfs/5707702298738688/google_transit.zip",
            "i": "http://opentrans.it/"
          }
        },
        "id": "opentransit/352/20150329-2",
        "size": 11293,
        "ts": 1427693179,
        "url": "https://transitfeeds.com/p/opentransit/352/20150329-2/download"
      },
      {
        "d": {
          "f": "20150502",
          "s": "20150104"
        },
        "f": {
          "id": "chattanooga-area-regional-transportation-authority/360",
          "l": {
            "id": 265,
            "lat": 35.04563,
            "lng": -85.30968,
            "n": "Chattanooga",
            "pid": 174,
            "t": "Chattanooga, TN, USA"
          },
          "t": "CARTA GTFS",
          "ty": "gtfs",
          "u": {
            "d": "https://www.gocarta.org/developers/GTFS.zip",
            "i": "http://www.gocarta.org/#developers"
          }
        },
        "id": "chattanooga-area-regional-transportation-authority/360/20150329",
        "size": 907026,
        "ts": 1427677203,
        "url": "https://transitfeeds.com/p/chattanooga-area-regional-transportation-authority/360/20150329/download"
      },
      {
        "d": {
          "f": "20150613",
          "s": "20150201"
        },
        "f": {
          "id": "lane-transit-district/314",
          "l": {
            "id": 225,
            "lat": 44.052069,
            "lng": -123.086754,
            "n": "Eugene",
            "pid": 63,
            "t": "Eugene, OR, USA"
          },
          "t": "LTD GTFS",
          "ty": "gtfs",
          "u": {
            "d": "http://www.ltd.org/googletripplanning/20060917/google_transit.zip"
          }
        },
        "id": "lane-transit-district/314/20150329",
        "size": 1141600,
        "ts": 1427657702,
        "url": "https://transitfeeds.com/p/lane-transit-district/314/20150329/download"
      }
    ]
  },
  "status": "OK",
  "ts": 1617078714
}